Workbook

Sheet PORTADA
B3: PRESUPUESTO DE OBRA BIM
B4: Torre Santa Isabel · CVA Constructora
B5: Vinculado al modelo IFC · 186 partidas BIM
B10: DATOS DEL PROYECTO
B12: Proyecto | C12: Torre Santa Isabel
B13: Contratista | C13: CVA Constructora
B14: Director de obra | C14: Miguel Salazar
B15: Fecha base | C15: 01/May/2026
B16: Fecha fin proyecto | C16: 16/Feb/2028
B17: Plazo total (días) | C17: 656
B18: Modelo IFC | C18: STA_ISABEL_v3.ifc
B19: Versión presupuesto | C19: 1
B22: KPI EJECUTIVOS (auto-calculados)
B24: Presupuesto total | C24: =Resumen!C5
B25: Comprometido | C25: =Resumen!C6
B26: Ejecutado | C26: =Resumen!C7
B27: CPI | C27: =Resumen!C13
B28: Desviación total | C28: =Resumen!C9
B29: Proyección EAC | C29: =Resumen!C14
B33: Convención de colores: AZUL = inputs (editables) · NEGRO = fórmulas · VERDE = referencias entre hojas. NUNCA escribir en celdas negras.

Sheet EDT
A1: EDT · ESTRUCTURA DE DESGLOSE DE TRABAJO
A2: Editar solo columnas AZULES (Metrado, V.Unit, Ejec). Las columnas en NEGRO se calculan automáticamente. Capítulos (filas grises) suman sus partidas.
A3: Código | B3: Descripción | C3: BIM | D3: Unidad | E3: Metrado | F3: V. Unit. | G3: Presupuesto | H3: Ejecutado | I3: % Ejec.
A4: 01 | B4: Preliminares | G4: =SUMIFS(G4:G99,A4:A99,"01.*") | H4: =SUMIFS(H4:H99,A4:A99,"01.*") | I4: =IFERROR(H4/G4,0)
A5: 01.01 | B5: Cerramiento provisional | D5: ml | E5: 240 | F5: 85000 | G5: =E5*F5 | H5: 20000000 | I5: =IFERROR(H5/G5,0)
A6: 01.02 | B6: Descapote y limpieza | D6: m² | E6: 1800 | F6: 12000 | G6: =E6*F6 | H6: 21000000 | I6: =IFERROR(H6/G6,0)
A7: 02 | B7: Estructura | G7: =SUMIFS(G4:G99,A4:A99,"02.*") | H7: =SUMIFS(H4:H99,A4:A99,"02.*") | I7: =IFERROR(H7/G7,0)
A8: 02.01 | B8: Excavación manual | D8: m³ | E8: 3200 | F8: 45000 | G8: =E8*F8 | H8: 144000000 | I8: =IFERROR(H8/G8,0)
A9: 02.02 | B9: Pilotes D=60cm | D9: ml | E9: 860 | F9: 280000 | G9: =E9*F9 | H9: 241000000 | I9: =IFERROR(H9/G9,0)
A10: 02.03 | B10: Concreto muros cimentación | C10: BIM | D10: m³ | E10: 420 | F10: 380000 | G10: =E10*F10 | H10: 188000000 | I10: =IFERROR(H10/G10,0)
A11: 02.04 | B11: Acero longitudinal Ø3/8" | D11: kg | E11: 48000 | F11: 3800 | G11: =E11*F11 | H11: 25000000 | I11: =IFERROR(H11/G11,0)
A12: 02.05 | B12: Estructura sótanos nivel -3 | C12: BIM | D12: m² | E12: 2400 | F12: 520000 | G12: =E12*F12 | H12: 0 | I12: =IFERROR(H12/G12,0)
A13: 03 | B13: MEP | G13: =SUMIFS(G4:G99,A4:A99,"03.*") | H13: =SUMIFS(H4:H99,A4:A99,"03.*") | I13: =IFERROR(H13/G13,0)
A14: 03.01 | B14: Red hidrosanitaria | D14: pto | E14: 840 | F14: 320000 | G14: =E14*F14 | H14: 0 | I14: =IFERROR(H14/G14,0)
A15: 03.02 | B15: Red eléctrica circuitos | D15: pto | E15: 1200 | F15: 185000 | G15: =E15*F15 | H15: 0 | I15: =IFERROR(H15/G15,0)
A16: 04 | B16: Acabados | G16: =SUMIFS(G4:G99,A4:A99,"04.*") | H16: =SUMIFS(H4:H99,A4:A99,"04.*") | I16: =IFERROR(H16/G16,0)
A17: 04.01 | B17: Mortero de nivelación pisos | D17: m² | E17: 4200 | F17: 38000 | G17: =E17*F17 | H17: 0 | I17: =IFERROR(H17/G17,0)
A18: 04.02 | B18: Enchape cerámico baños | D18: m² | E18: 680 | F18: 120000 | G18: =E18*F18 | H18: 0 | I18: =IFERROR(H18/G18,0)
A19: 05 | B19: Urbanismo y exteriores | G19: =SUMIFS(G4:G99,A4:A99,"05.*") | H19: =SUMIFS(H4:H99,A4:A99,"05.*") | I19: =IFERROR(H19/G19,0)
A20: 05.01 | B20: Adoquines vehiculares | D20: m² | E20: 450 | F20: 88000 | G20: =E20*F20 | H20: 0 | I20: =IFERROR(H20/G20,0)
A21: TOTAL | B21: Presupuesto base del proyecto | G21: =SUM(G4,G7,G13,G16,G19) | H21: =SUM(H4,H7,H13,H16,H19) | I21: =IFERROR(H21/G21,0)

Sheet APU
A1: APU · ANÁLISIS DE PRECIOS UNITARIOS
A2: Plantilla APU para partidas BIM. Cambiar partida en C4 para recalcular. Costo total unit. se transfiere automático al EDT.
A4: Partida actual: | C4: 02.03 Concreto muros cimentación
A5: BIM vinculado: | C5: Sí (modelo IFC, 420 m³)
A7: 1. MATERIALES
A8: Descripción | B8: Unidad | C8: Cantidad | D8: Desperdicio % | E8: V. Unit. | F8: Subtotal
A9: Concreto 3000 PSI | B9: m³ | C9: 0.95 | D9: 0.05 | E9: 360000 | F9: =C9*(1+D9)*E9
A10: Acero corrugado 3/8" | B10: kg | C10: 95 | D10: 0.03 | E10: 3800 | F10: =C10*(1+D10)*E10
A11: Formaleta metálica | B11: m² | C11: 2 | D11: 0.02 | E11: 20000 | F11: =C11*(1+D11)*E11
A12: Aditivos plastificantes | B12: lt | C12: 1.5 | D12: 0 | E12: 12000 | F12: =C12*(1+D12)*E12
A13: Subtotal materiales (por m³) | F13: =SUM(F9:F12)
A15: 2. MANO DE OBRA Y EQUIPO
A16: Recurso | B16: Unidad | C16: Rendimiento | D16: Prestaciones % | E16: Jornal/Tarifa | F16: Subtotal
A17: Oficial concreto | B17: jor | C17: 0.8 | D17: 0.35 | E17: 65000 | F17: =C17*(1+D17)*E17
A18: Ayudante | B18: jor | C18: 1.6 | D18: 0.35 | E18: 45000 | F18: =C18*(1+D18)*E18
A19: Vibrador concreto | B19: hr | C19: 0.5 | D19: 0 | E19: 18000 | F19: =C19*(1+D19)*E19
A20: Bomba concreto | B20: hr | C20: 0.25 | D20: 0 | E20: 85000 | F20: =C20*(1+D20)*E20
A21: Subtotal MO + Equipo (por m³) | F21: =SUM(F17:F20)
A23: 3. RESUMEN COSTOS
A25: Costo directo (materiales + MO) | F25: =F13+F21
A26: AIU % (Admin + Imprev. + Util.) | F26: 0.3
A27: AIU absoluto | F27: =F25*F26
A28: Costo total unitario (presup.) | F28: =F25+F27
A29: Costo unitario REAL (ejecutado) | F29: =EDT!H10/EDT!E10
A30: Desviación absoluta | F30: =F29-F28
A31: Desviación % | F31: =IFERROR(F30/F28,0)

Sheet OrdenesCambio
A1: ÓRDENES DE CAMBIO (OCC)
A2: Registro de cambios al presupuesto. La suma alimenta automáticamente el Resumen → desviación total.
A3: Código | B3: Descripción | C3: Partida afectada | D3: Fase | E3: Valor aprobado | F3: Impacto plazo (días) | G3: Solicitado por | H3: Estado
A4: OC-C001 | B4: Sobrecosto concreto muros | C4: 02.03 | D4: F2 | E4: 28000000 | F4: 0 | G4: R. Gómez | H4: En revisión
A5: OC-C002 | B5: Refuerzo adicional pilotes | C5: 02.02 | D5: F1 | E5: 14000000 | F5: 3 | G5: C. Torres | H5: Aprobada
A6: OC-C003 | B6: Cambio especificación acero | C6: 02.04 | D6: F2 | E6: 8000000 | F6: 2 | G6: R. Gómez | H6: Borrador
A8: TOTAL | B8: Valor aprobado (suma 3 OCC) | E8: =SUM(E4:E7) | F8: =SUM(F4:F7)

Sheet Resumen
A1: RESUMEN EJECUTIVO · EVM
A2: Indicadores Earned Value Management calculados desde EDT + OrdenesCambio.
B5: Presupuesto base (sin OCC) | C5: =EDT!G21 | D5: Línea base aprobada
B6: Comprometido | C6: =EDT!G21*0.26 | D6: 26% del total (sim.)
B7: Ejecutado real (AC) | C7: =EDT!H21 | D7: Suma de columna Ejec del EDT
B8: Sobrecosto por OCC | C8: =OrdenesCambio!E8 | D8: Suma órdenes de cambio
B9: Desviación total | C9: =C7+C8-C5 | D9: Ejec + OCC - Presup
B11: Valor planificado (PV) | C11: =EDT!G21*0.09 | D11: PV al corte de hoy
B12: Valor ganado (EV) | C12: =C7*0.91 | D12: EV = AC × CPI
B13: Costo real (AC) | C13: =C7 | D13: Igual a Ejecutado
B14: CPI (Cost Performance Idx) | C14: =IFERROR(C12/C13,0) | D14: EV / AC — > 1 = bajo presup.
B15: EAC (Estimate at Completion) | C15: =IFERROR(C5/C14,0) | D15: Presup / CPI
B16: VAC (Variance at Completion) | C16: =C5-C15 | D16: Presup - EAC
B17: SPI (Schedule Performance) | C17: =IFERROR(C12/C11,0) | D17: EV / PV
B20: CONCLUSIÓN GERENCIAL
B21: =IF(C14<1,"⚠ CPI < 1.00 — el proyecto está gastando más de lo presupuestado. ","✓ CPI ≥ 1.00 — el proyecto está dentro o por debajo del presupuesto. ")&"Proyección EAC: "&TEXT(C15,"$#,##0")&". "&IF(C9>0,"Hay "&TEXT(C9,"$#,##0")&" en órdenes de cambio acumuladas.","Sin órdenes de cambio.")
